smartConvDS/__init__.py
smartConvDS/main.py
smartConvDS/run_converter.py
smartConvDS-0.2a0.dist-info/METADATA
smartConvDS-0.2a0.dist-info/WHEEL
smartConvDS-0.2a0.dist-info/top_level.txt
smartConvDS-0.2a0.dist-info/RECORD
